stoclust/Aggregation.py
stoclust/Group.py
stoclust/Hierarchy.py
stoclust/__init__.py
stoclust/clustering.py
stoclust/distance.py
stoclust/ensemble.py
stoclust/examples.py
stoclust/gram.py
stoclust/regulators.py
stoclust/similarity.py
stoclust/simulation.py
stoclust/utils.py
stoclust/visualization.py
stoclust-0.1.6.dist-info/LICENSE
stoclust-0.1.6.dist-info/METADATA
stoclust-0.1.6.dist-info/WHEEL
stoclust-0.1.6.dist-info/top_level.txt
stoclust-0.1.6.dist-info/RECORD
