Metadata-Version: 2.1
Name: stoclust
Version: 0.1.6
Summary: Modular methods for stochastic clustering
Home-page: UNKNOWN
Author: Samuel Loomis
Author-email: sloomis@ucdavis.edu
License: UNKNOWN
Platform: UNKNOWN
License-File: LICENSE
Requires-Dist: numpy (>=1.15.0)
Requires-Dist: scipy (>=1.1.0)
Requires-Dist: plotly (>=4.12.0)
Requires-Dist: tqdm (>=4.41.1)
Requires-Dist: pandas (>=0.25.0)
